{
  "ads": [
    {
      "appName": "Photo Editor Pro",
      "pubName": "PIXEL PHOTO PRO",
      "icon": "https://lh3.googleusercontent.com/RxaRcb-ws056FQnb0SNYM-bOmnJ4zUKX-K4ITxuZRpBJnVII4gYgR4kLg5_za8zUON0=w300-rw",
      "description": "Photo Editor Pro is the most popular photo editor application for selfie photos.",
      "promotionPhoto": "https://lh3.googleusercontent.com/JuKV04iVZ7xeJLLQzaqqOzeOh9rDPONM1OvHmuLPmPRt4CC2g1bLF8k3gPx-k9Imvg=h900-rw",
      "promotionLink": "https://play.google.com/store/apps/details?id=pixel.photo.pro.photo.editor",
      "packageName": "pixel.photo.pro.photo.editor"
    }
  ],
  "promotedPackage": "pixel.photo.pro.photo.editor",
  "promotedLink": ""
}