{
  "ads": [
    {
      "appName": "Pretty Photo Frames",
      "pubName": "Blue Sky Studio",
      "icon": "https://lh3.googleusercontent.com/f5amWDrchQPc0WOWPP1BLtZKyOAldE_eAJp5EWTHVqLsW-oHUvhR_K8IyNy_WyxsXgxE=w300-rw",
      "description": "Pretty Photo Frames is the best ever on the app store.",
      "promotionPhoto": "https://lh3.googleusercontent.com/KY8W4KQ2XRXdyHiUBCkGOSessljROsAtgJB7idLe-_sIsaw9ILR_uC6hgsgJzrxIs6k=h900-rw",
      "promotionLink": "https://play.google.com/store/apps/details?id=bt.PhotoFrameGird.pretty.frames.PrettyFramePhoto",
      "packageName": "bt.PhotoFrameGird.pretty.frames.PrettyFramePhoto"
    },
    {
      "appName": "Christmas Collage Editor",
      "pubName": "Blue Sky Studio",
      "icon": "https://lh3.googleusercontent.com/JreNV1-59ik0eE_2sVeI5GUky35EjrycXmwM9uegVV28FUw-PAzO-N8KrnKMjsuaObYH=w300-rw",
      "description": "Christmas Photo Frames is a powerful photo editor with many amazing effects and fitters.",
      "promotionPhoto": "https://lh3.googleusercontent.com/YJvVsWpMey5D-_2HipCYtxjgtuy1p4A2Uvig5S3iRYqIXfHTjNQzxqnmCAxs4KSWSDU=h900-rw",
      "promotionLink": "https://play.google.com/store/apps/details?id=bs.photoFrame.photoGird.Christmas",
      "packageName": "bs.photoFrame.photoGird.Christmas"
    }
  ]
}